MANIFEST.in
README.rst
setup.py
bin/pypacker
bin/rambo
bin/rambo_sprites.sh
rambo/__init__.py
rambo/__main__.py
rambo/rambo.py
rambo.egg-info/PKG-INFO
rambo.egg-info/SOURCES.txt
rambo.egg-info/dependency_links.txt
rambo.egg-info/not-zip-safe
rambo.egg-info/requires.txt
rambo.egg-info/top_level.txt