Metadata-Version: 1.0
Name: rambo
Version: 0.1.1.1
Summary: Ram your images into CSS sprites with Rambo
Home-page: https://github.com/springload/rambo
Author: Springload
Author-email: josh@springload.co.nz
License: MIT
Platform: UNKNOWN
